[
  {
    "date": "2026-06-14",
    "title": "“아차한 사이 완판, 두번째엔 제발”…2차 국민성장펀드, 3분기 출시"
  },
  {
    "date": "2026-06-14",
    "title": "초고액예금 썰물에…은행, 자산관리 안간힘"
  },
  {
    "date": "2026-06-14",
    "title": "초고액예금 썰물에…은행, 자산관리 안간힘"
  },
  {
    "date": "2026-06-14",
    "title": "은행점포 줄어든 지역 신생기업 수도 감소"
  },
  {
    "date": "2026-06-15",
    "title": "어르신도 로펌도 “치매머니 못잃어”…노후돌봄 뛰어든 법무법인"
  },
  {
    "date": "2026-06-15",
    "title": "정부 '한은 마통' 1년 새 60% 급감"
  },
  {
    "date": "2026-06-15",
    "title": "“아차한 사이 완판, 두번째엔 제발”…2차 국민성장펀드, 3분기 출시"
  }
]